easy_mi_cybergear/__init__.py
easy_mi_cybergear/answer_frame.py
easy_mi_cybergear/can_id_and_communication_type.py
easy_mi_cybergear/easy_mi_cybergear.py
easy_mi_cybergear/log.py
easy_mi_cybergear/utils.py
easy_mi_cybergear-1.0.5.dist-info/METADATA
easy_mi_cybergear-1.0.5.dist-info/WHEEL
easy_mi_cybergear-1.0.5.dist-info/RECORD
