Metadata-Version: 2.3
Name: easy_mi_cybergear
Version: 1.0.5
Summary: 使用python通过USB-CAN模块轻松控制小米cybergear微电机
Keywords: cybergear,小米cybergear微电机,小米微电机,python,USB-CAN
Author: qllokirin
Requires-Python: >=3.9,<4.0
Classifier: Programming Language :: Python :: 3
Classifier: Programming Language :: Python :: 3.9
Classifier: Programming Language :: Python :: 3.10
Classifier: Programming Language :: Python :: 3.11
Classifier: Programming Language :: Python :: 3.12
Classifier: Programming Language :: Python :: 3.13
Requires-Dist: colorlog (>=6.9.0,<7.0.0)
Requires-Dist: pyserial (>=3.5,<4.0)
